Workbook

Sheet Executive Roadmap
A1: Sprint | B1: Theme | C1: Objective | D1: Workstream | E1: Start | F1: End | G1: Status | H1: Story Points | I1: Story Count | J1: Exit Gate
A2: S0 | B2: Architecture Baseline | C2: Freeze scope, risks, contracts and environments | D2: Architecture | E2: 46307 | F2: 46318 | G2: Planned | H2: =SUMIF('Sprint Backlog'!$C:$C,A2,'Sprint Backlog'!$H:$H) -> 0 | I2: =COUNTIF('Sprint Backlog'!$C:$C,A2) -> 0 | J2: Architecture, threat model and backlog approved
A3: S1 | B3: Contracts and Identity | C3: Schemas, signing identities and IPC skeleton | D3: Platform | E3: 46321 | F3: 46332 | G3: Planned | H3: =SUMIF('Sprint Backlog'!$C:$C,A3,'Sprint Backlog'!$H:$H) -> 0 | I3: =COUNTIF('Sprint Backlog'!$C:$C,A3) -> 0 | J3: Integrated increment demonstrated
A4: S2 | B4: Policy Core | C4: OPA, immutable policy, risk and tests | D4: Security | E4: 46335 | F4: 46346 | G4: Planned | H4: =SUMIF('Sprint Backlog'!$C:$C,A4,'Sprint Backlog'!$H:$H) -> 0 | I4: =COUNTIF('Sprint Backlog'!$C:$C,A4) -> 0 | J4: Integrated increment demonstrated
A5: S3 | B5: Approval and Evidence | C5: Trusted approval, stop, audit and telemetry | D5: Security | E5: 46349 | F5: 46360 | G5: Planned | H5: =SUMIF('Sprint Backlog'!$C:$C,A5,'Sprint Backlog'!$H:$H) -> 0 | I5: =COUNTIF('Sprint Backlog'!$C:$C,A5) -> 0 | J5: No action can bypass policy, approval or audit
A6: S4 | B6: Cognitive Runtime | C6: LangGraph, model gateway and checkpoints | D6: Agent | E6: 46363 | F6: 46374 | G6: Planned | H6: =SUMIF('Sprint Backlog'!$C:$C,A6,'Sprint Backlog'!$H:$H) -> 0 | I6: =COUNTIF('Sprint Backlog'!$C:$C,A6) -> 0 | J6: Integrated increment demonstrated
A7: S5 | B7: Safe Windows Broker | C7: App/window/media capabilities and leases | D7: Windows | E7: 46377 | F7: 46388 | G7: Planned | H7: =SUMIF('Sprint Backlog'!$C:$C,A7,'Sprint Backlog'!$H:$H) -> 0 | I7: =COUNTIF('Sprint Backlog'!$C:$C,A7) -> 0 | J7: Integrated increment demonstrated
A8: S6 | B8: Verification and Recovery | C8: Evidence, idempotency and uncertainty | D8: Reliability | E8: 46391 | F8: 46402 | G8: Planned | H8: =SUMIF('Sprint Backlog'!$C:$C,A8,'Sprint Backlog'!$H:$H) -> 0 | I8: =COUNTIF('Sprint Backlog'!$C:$C,A8) -> 0 | J8: Verified/failed/uncertain behavior proven
A9: S7 | B9: Privacy and Perception | C9: UIA, exclusions, labels and redaction | D9: Privacy | E9: 46405 | F9: 46416 | G9: Planned | H9: =SUMIF('Sprint Backlog'!$C:$C,A9,'Sprint Backlog'!$H:$H) -> 0 | I9: =COUNTIF('Sprint Backlog'!$C:$C,A9) -> 0 | J9: Integrated increment demonstrated
A10: S8 | B10: Tool Platform Core | C10: Catalog, retrieval, grants and runtime | D10: Tools | E10: 46419 | F10: 46430 | G10: Planned | H10: =SUMIF('Sprint Backlog'!$C:$C,A10,'Sprint Backlog'!$H:$H) -> 0 | I10: =COUNTIF('Sprint Backlog'!$C:$C,A10) -> 0 | J10: Integrated increment demonstrated
A11: S9 | B11: Initial MCP Pack | C11: Restricted browser/file/git/document/search tools | D11: Tools | E11: 46433 | F11: 46444 | G11: Planned | H11: =SUMIF('Sprint Backlog'!$C:$C,A11,'Sprint Backlog'!$H:$H) -> 0 | I11: =COUNTIF('Sprint Backlog'!$C:$C,A11) -> 0 | J11: Initial MCP pack isolated and contract-pinned
A12: S10 | B12: Voice | C12: Wake, VAD, STT, TTS and interruption | D12: Interaction | E12: 46447 | F12: 46458 | G12: Planned | H12: =SUMIF('Sprint Backlog'!$C:$C,A12,'Sprint Backlog'!$H:$H) -> 0 | I12: =COUNTIF('Sprint Backlog'!$C:$C,A12) -> 0 | J12: Integrated increment demonstrated
A13: S11 | B13: 3D Character | C13: Asset MVP, Godot overlay and animation states | D13: Character | E13: 46461 | F13: 46472 | G13: Planned | H13: =SUMIF('Sprint Backlog'!$C:$C,A13,'Sprint Backlog'!$H:$H) -> 0 | I13: =COUNTIF('Sprint Backlog'!$C:$C,A13) -> 0 | J13: Voice and character usable as one experience
... A19: S17 | B19: Beta and Release | C19: Installer, pilot, documentation and gates | D19: Release | E19: 46545 | F19: 46556 | G19: Planned | H19: =SUMIF('Sprint Backlog'!$C:$C,A19,'Sprint Backlog'!$H:$H) -> 0 | I19: =COUNTIF('Sprint Backlog'!$C:$C,A19) -> 0 | J19: Production readiness review approves beta release

Sheet Sprint Backlog
A1: Story ID | B1: Story | C1: Sprint | D1: Sprint Theme | E1: Workstream | F1: Owner Role | G1: Priority | H1: Points | I1: Dependencies | J1: Acceptance Criterion | K1: Status
A2: ARCH-001 | B2: Approve architecture decision record set | C2: S0 | D2: Architecture Baseline | E2: Architecture | F2: Lead Architect | G2: Must | H2: 5 | I2: None | J2: Architecture v1 signed off | K2: Planned
A3: SEC-001 | B3: Create threat model and trust-boundary data-flow diagrams | C3: S0 | D3: Architecture Baseline | E3: Security | F3: Security Engineer | G3: Must | H3: 8 | I3: None | J3: Threats mapped to controls | K3: Planned
A4: PLAT-001 | B4: Create monorepo, CI quality gates and environments | C4: S0 | D4: Architecture Baseline | E4: Platform | F4: Platform Engineer | G4: Must | H4: 8 | I4: None | J4: Clean build/test pipeline | K4: Planned
A5: UX-001 | B5: Convert character references into production asset brief | C5: S0 | D5: Architecture Baseline | E5: Character | F5: 3D/UX Artist | G5: Must | H5: 5 | I5: None | J5: Brief covers rig, LOD and accessories | K5: Planned
A6: PM-001 | B6: Baseline outcomes, scope, risks and sprint governance | C6: S0 | D6: Architecture Baseline | E6: Program | F6: Product Owner | G6: Must | H6: 3 | I6: None | J6: Backlog and gates approved | K6: Planned
A7: CON-001 | B7: Define Task, ActionIntent and expected-effect schemas | C7: S1 | D7: Contracts and Identity | E7: Contracts | F7: Platform Engineer | G7: Must | H7: 8 | I7: S0 | J7: Schemas validated with examples | K7: Planned
A8: CON-002 | B8: Define policy decision, approval and capability grant schemas | C8: S1 | D8: Contracts and Identity | E8: Contracts | F8: Security Engineer | G8: Must | H8: 8 | I8: S0 | J8: Signature fields and expiry specified | K8: Planned
A9: CON-003 | B9: Define normalized result, evidence and audit schemas | C9: S1 | D9: Contracts and Identity | E9: Contracts | F9: Reliability Engineer | G9: Must | H9: 5 | I9: S0 | J9: Versioned compatibility tests pass | K9: Planned
A10: IPC-001 | B10: Prototype ACL-protected named-pipe service identity | C10: S1 | D10: Contracts and Identity | E10: Platform | F10: Windows Engineer | G10: Must | H10: 8 | I10: S0 | J10: Unauthorized clients rejected | K10: Planned
A11: POL-001 | B11: Deploy local OPA service and signed policy bundles | C11: S2 | D11: Policy Core | E11: Security | F11: Security Engineer | G11: Must | H11: 8 | I11: S1 | J11: Bundle signature/version enforced | K11: Planned
A12: POL-002 | B12: Implement R0–R4 deterministic risk classifier | C12: S2 | D12: Policy Core | E12: Security | F12: Security Engineer | G12: Must | H12: 8 | I12: S1 | J12: Risk matrix tests pass | K12: Planned
A13: POL-003 | B13: Implement immutable root restrictions | C13: S2 | D13: Policy Core | E13: Security | F13: Windows Engineer | G13: Must | H13: 8 | I13: S1 | J13: Conversation cannot modify restrictions | K13: Planned
... A79: GATE-001 | B79: Conduct production readiness review | C79: S17 | D79: Beta and Release | E79: Governance | F79: Architecture Board | G79: Must | H79: 5 | I79: S16 | J79: Go/no-go decision recorded | K79: Planned

Sheet Architecture Workstreams
A1: Workstream | B1: Primary Deliverables | C1: Key Interfaces | D1: Primary Owner | E1: Quality Evidence | F1: Target Sprints
A2: Experience/Character | B2: 3D asset, Godot overlay, semantic animation and status UI | C2: Interaction events; trusted UI separation | D2: Godot + 3D Team | E2: DPI, multi-monitor, frame time and accessibility tests | F2: S0, S10–S11
A3: Interaction | B3: Wake/VAD/STT/TTS, barge-in and privacy controls | C3: Orchestrator and character cues | D3: Interaction Engineer | E3: False-wake, latency and interruption metrics | F3: S10–S11
A4: Agent Orchestration | B4: LangGraph graphs, planning, checkpoints and recovery | C4: LLM gateway, policy and tool platform | D4: AI Engineer | E4: Bounded loop and crash/replay tests | F4: S4 onward
A5: Policy/Guardrails | B5: OPA, PEP/PIP, risk, approvals and grants | C5: All effectful paths | D5: Security Engineer | E5: Policy matrix and adversarial suite | F5: S1–S3, S16
A6: Windows | B6: Signed brokers, UIA, process containment and leases | C6: Policy grants and verifier | D6: Windows Engineer | E6: Publisher/target/takeover tests | F6: S5–S7, S14
A7: Tool Platform | B7: Registry, retrieval, contracts, isolation and MCP portfolio | C7: LangGraph, OPA and verifier | D7: Platform/Tool Engineer | E7: Contract drift and sandbox tests | F7: S8–S9, S13
A8: Privacy | B8: Exclusions, labels, redaction and release policy | C8: Sensors, LLM, memory and telemetry | D8: Privacy Engineer | E8: Leakage and excluded-app tests | F8: S7, S12, S16
A9: Verification | B9: Predicates, evidence, idempotency and uncertainty | C9: Every effectful capability | D9: Reliability Engineer | E9: No duplicate effects; evidence coverage | F9: S6 onward
A10: Memory | B10: Classes, admission, retrieval, provenance and deletion | C10: Orchestrator and privacy | D10: Data/AI Engineer | E10: Poisoning and deletion tests | F10: S12
A11: Observability/Audit | B11: OTel stack, action review and hash-chained journal | C11: All components | D11: SRE | E11: Trace completeness and tamper checks | F11: S3 onward

Sheet Risk Register
A1: Risk ID | B1: Risk | C1: Probability | D1: Impact | E1: Rating | F1: Mitigation | G1: Trigger/Indicator | H1: Owner | I1: Review Sprint | J1: Status
A2: R-01 | B2: Indirect prompt injection causes tool misuse | C2: High | D2: Critical | E2: Critical | F2: Data/instruction separation, taint, OPA, destination checks and adversarial tests | G2: Observed content attempts to alter goal/authority | H2: Security Engineer | I2: Every sprint | J2: Open
A3: R-02 | B3: MCP supply-chain compromise | C3: Medium | D3: Critical | E3: High | F3: Pin digests, SBOM/scan, isolation, egress/mount controls and quarantine | G3: Schema/digest/dependency changes | H3: Tool Platform Lead | I3: S8–S16 | J3: Open
A4: R-03 | B4: Private context reaches remote endpoint or telemetry | C4: Medium | D4: Critical | E4: High | F4: Local source policy, release views, secret tests and telemetry allowlists | G4: Secret canary appears outside privacy boundary | H4: Privacy Engineer | I4: S7–S16 | J4: Open
A5: R-04 | B5: UI automation targets wrong window or element | C5: High | D5: High | E5: High | F5: Publisher identity, fresh UIA snapshot, confidence margin and verification | G5: Focus/layout/DPI change between plan and action | H5: Windows Engineer | I5: S5–S16 | J5: Open
A6: R-05 | B6: Retry duplicates external effect | C6: Medium | D6: Critical | E6: High | F6: Idempotency registry, prepare/commit and stop on uncertainty | G6: Timeout after effect with missing response | H6: Reliability Engineer | I6: S6 onward | J6: Open
A7: R-06 | B7: User mistakes character prompt for trusted approval | C7: Medium | D7: High | E7: High | F7: Separate signed native approval UI and consistent trusted visual language | G7: Approval shown inside avatar/website | H7: Security UX | I7: S3 onward | J7: Open
A8: R-07 | B8: Character asset/overlay misses performance target | C8: Medium | D8: Medium | E8: Medium | F8: LOD, bounded physics, early Godot spike and frame-time budget | G8: High GPU/CPU or input interference | H8: Godot Lead | I8: S0, S11 | J8: Open
A9: R-08 | B9: Voice latency or false wakes harm trust | C9: Medium | D9: Medium | E9: Medium | F9: Local VAD/wake, model benchmarks, push-to-talk and latency telemetry | G9: False wake/response latency exceeds threshold | H9: Interaction Lead | I9: S10 | J9: Open
A10: R-09 | B10: Memory stores false or poisoned instructions | C10: Medium | D10: High | E10: High | F10: Quarantine, provenance, contradiction checks and no executable remembered text | G10: Untrusted claim retrieved as workflow | H10: Memory Lead | I10: S12–S16 | J10: Open
A11: R-10 | B11: Tool breadth creates unreliable selection | C11: High | D11: Medium | E11: High | F11: Progressive retrieval, initial 10–15 tools and selection evaluation | G11: Incorrect-tool/policy-denial rate rises | H11: AI/Tool Lead | I11: S8 onward | J11: Open
A12: R-11 | B12: Target hardware cannot run full local stack | C12: Medium | D12: Medium | E12: Medium | F12: Baseline target hardware; configurable services; performance spike | G12: Sustained resource budget breach | H12: SRE | I12: S0, S10–S16 | J12: Open
A13: R-12 | B13: Audit/trace storage leaks content or grows unbounded | C13: Medium | D13: High | E13: High | F13: Field allowlists, retention tiers, quotas, encryption and review | G13: Unexpected content/cardinality/storage growth | H13: SRE/Privacy | I13: S3 onward | J13: Open

Sheet Acceptance Gates
A1: Gate | B1: Target Sprint | C1: Required Evidence | D1: Pass Condition | E1: Owner | F1: Status
A2: G0 Architecture | B2: S0 | C2: ADRs, scope, threat model, data flow and backlog | D2: Architecture board approves baseline | E2: Lead Architect | F2: Planned
A3: G1 Control Plane | B3: S3 | C3: Policy tests, approval signatures, emergency stop and audit chain | D3: No tested effect path bypasses controls | E3: Security Lead | F3: Planned
A4: G2 Safe Actuation | B4: S6 | C4: Broker/lease, idempotency and independent verification suite | D4: Zero duplicate effects; uncertainty stops | E4: Reliability Lead | F4: Planned
A5: G3 Privacy | B5: S7 | C5: Excluded-app, release-view, private-mode and telemetry leak tests | D5: Prohibited data does not cross boundary | E5: Privacy Lead | F5: Planned
A6: G4 Tool Platform | B6: S9 | C6: Pinned contracts, isolation, egress/mount and drift tests | D6: All production tools pass onboarding | E6: Tool Platform Lead | F6: Planned
A7: G5 Experience | B7: S11 | C7: Voice latency, barge-in, avatar state and multi-monitor tests | D7: Integrated experience meets usability baseline | E7: Experience Lead | F7: Planned
A8: G6 Memory | B8: S12 | C8: Admission, provenance, poisoning and deletion evidence | D8: No prohibited/executable poisoned memory | E8: Memory Lead | F8: Planned
A9: G7 Supervised Agent | B9: S14 | C9: UI ambiguity, takeover, workflow draft and end-to-end tests | D9: Supervised actions remain bounded and explainable | E9: Product/Safety | F9: Planned
A10: G8 Security Hardening | B10: S16 | C10: Red-team, privacy, DR and performance reports | D10: No critical finding; thresholds achieved | E10: Security/QA | F10: Planned
A11: G9 Production Readiness | B11: S17 | C11: Pilot results, signed installer, runbooks and dashboards | D11: Go decision recorded by review board | E11: Architecture Board | F11: Planned

Sheet RACI
A1: Deliverable | B1: Accountable | C1: Responsible | D1: Consulted | E1: Informed
A2: Architecture baseline | B2: Lead Architect | C2: Architecture Team | D2: Security, Product, Windows, AI | E2: All workstreams
A3: Policy and immutable restrictions | B3: Security Lead | C3: Security + Windows Engineers | D3: Privacy, Legal/Product | E3: All capability owners
A4: Trusted approval experience | B4: Security Lead | C4: Windows + UX Engineers | D4: Product, Accessibility | E4: Users/pilot
A5: LangGraph and model gateway | B5: AI Lead | C5: AI + Platform Engineers | D5: Security, Privacy, SRE | E5: Product
A6: Windows capability broker | B6: Windows Lead | C6: Windows Engineers | D6: Security, Reliability | E6: AI/Tool teams
A7: Tool Capability Platform | B7: Platform Lead | C7: Tool + Platform Engineers | D7: Security, AI, SRE | E7: Capability owners
A8: Privacy firewall | B8: Privacy Lead | C8: Privacy + Windows Engineers | D8: Security, Product | E8: All data processors
A9: Character and voice | B9: Experience Lead | C9: Godot/3D + Interaction Team | D9: Product, Accessibility, Performance | E9: Users/pilot
A10: Verification and audit | B10: Reliability Lead | C10: Reliability + SRE | D10: Security, Tool, Windows | E10: Architecture Board
A11: Production release | B11: Product Owner | C11: Release + QA + SRE | D11: All leads | E11: Stakeholders/users

Sheet Definition of Done
A1: Category | B1: Required Check | C1: Evidence | D1: Applies To
A2: Code | B2: Reviewed, formatted, static checks clean and maintainability accepted | C2: CI report and review | D2: All engineering stories
A3: Contracts | B3: Versioned schema and compatibility tests updated | C3: Contract test report | D3: APIs/events/tools
A4: Security | B4: Threat impact reviewed; least privilege and denial paths tested | C4: Threat note and security tests | D4: Capabilities/data flows
A5: Privacy | B5: Classification, release, retention and deletion behavior tested | C5: Privacy test evidence | D5: Personal/sensitive data
A6: Policy | B6: Allow/deny/ask and obligations covered | C6: OPA test matrix | D6: Effectful actions
A7: Reliability | B7: Timeout, cancellation, retry, crash and uncertainty paths tested | C7: Failure-injection report | D7: Runtime components
A8: Verification | B8: Independent postcondition predicates implemented | C8: Evidence fixtures | D8: Effectful capabilities
A9: Observability | B9: Trace/metric/log fields added without sensitive content | C9: OTel test/dashboard | D9: Services/workflows
A10: Audit | B10: Security-relevant decisions/effects produce chained events | C10: Audit verification | D10: Policies/actions
A11: UX | B11: States, errors, approval and accessibility are understandable | C11: Usability/accessibility review | D11: User-facing stories
A12: Documentation | B12: ADR/runbook/user docs updated | C12: Published documents | D12: Behavioral/operational change
A13: Demo | B13: Acceptance criterion demonstrated in clean environment | C13: Recorded sprint evidence | D13: All stories
